labml_nn/__init__.py
labml_nn/activations/__init__.py
labml_nn/activations/swish.py
labml_nn/activations/fta/__init__.py
labml_nn/activations/fta/experiment.py
labml_nn/adaptive_computation/__init__.py
labml_nn/adaptive_computation/parity.py
labml_nn/adaptive_computation/ponder_net/__init__.py
labml_nn/adaptive_computation/ponder_net/experiment.py
labml_nn/capsule_networks/__init__.py
labml_nn/capsule_networks/mnist.py
labml_nn/cfr/__init__.py
labml_nn/cfr/analytics.py
labml_nn/cfr/infoset_saver.py
labml_nn/cfr/kuhn/__init__.py
labml_nn/conv_mixer/__init__.py
labml_nn/conv_mixer/experiment.py
labml_nn/diffusion/__init__.py
labml_nn/diffusion/ddpm/__init__.py
labml_nn/diffusion/ddpm/evaluate.py
labml_nn/diffusion/ddpm/experiment.py
labml_nn/diffusion/ddpm/unet.py
labml_nn/diffusion/ddpm/utils.py
labml_nn/diffusion/stable_diffusion/__init__.py
labml_nn/diffusion/stable_diffusion/latent_diffusion.py
labml_nn/diffusion/stable_diffusion/util.py
labml_nn/diffusion/stable_diffusion/model/__init__.py
labml_nn/diffusion/stable_diffusion/model/autoencoder.py
labml_nn/diffusion/stable_diffusion/model/clip_embedder.py
labml_nn/diffusion/stable_diffusion/model/unet.py
labml_nn/diffusion/stable_diffusion/model/unet_attention.py
labml_nn/diffusion/stable_diffusion/sampler/__init__.py
labml_nn/diffusion/stable_diffusion/sampler/ddim.py
labml_nn/diffusion/stable_diffusion/sampler/ddpm.py
labml_nn/diffusion/stable_diffusion/scripts/__init__.py
labml_nn/diffusion/stable_diffusion/scripts/image_to_image.py
labml_nn/diffusion/stable_diffusion/scripts/in_paint.py
labml_nn/diffusion/stable_diffusion/scripts/text_to_image.py
labml_nn/distillation/__init__.py
labml_nn/distillation/large.py
labml_nn/distillation/small.py
labml_nn/experiments/__init__.py
labml_nn/experiments/arithmetic_dataset.py
labml_nn/experiments/cifar10.py
labml_nn/experiments/mnist.py
labml_nn/experiments/nlp_autoregression.py
labml_nn/experiments/nlp_classification.py
labml_nn/gan/__init__.py
labml_nn-0.5.1.dist-info/METADATA
labml_nn-0.5.1.dist-info/WHEEL
labml_nn-0.5.1.dist-info/top_level.txt
labml_nn-0.5.1.dist-info/RECORD
