Metadata-Version: 2.1
Name: labml-nn
Version: 0.5.1
Summary: 🧑‍🏫 Implementations/tutorials of deep learning papers with side-by-side notes 📝; including transformers (original, xl, switch, feedback, vit), optimizers (adam, radam, adabelief), gans(dcgan, cyclegan, stylegan2), 🎮 reinforcement learning (ppo, dqn), capsnet, distillation, diffusion, etc. 🧠
Home-page: https://github.com/labmlai/annotated_deep_learning_paper_implementations
Author: Varuna Jayasiri, Nipun Wijerathne
Author-email: vpjayasiri@gmail.com, hnipun@gmail.com
Project-URL: Documentation, https://nn.labml.ai
Keywords: machine learning
Classifier: Programming Language :: Python :: 3
Classifier: License :: OSI Approved :: MIT License
Classifier: Intended Audience :: Developers
Classifier: Intended Audience :: Science/Research
Classifier: Topic :: Scientific/Engineering
Classifier: Topic :: Scientific/Engineering :: Mathematics
Classifier: Topic :: Scientific/Engineering :: Artificial Intelligence
Classifier: Topic :: Software Development
Classifier: Topic :: Software Development :: Libraries
Classifier: Topic :: Software Development :: Libraries :: Python Modules
Requires-Dist: labml
Requires-Dist: torch
Requires-Dist: torchtext
Requires-Dist: torchvision
Requires-Dist: einops
Requires-Dist: numpy
Requires-Dist: fairscale
